.coveragerc
.gitignore
.travis.yml
.zerotk.uniform.yml
LICENSE.txt
README.md
pytest.ini
requirements.txt
setup.cfg
setup.py
tasks.py
docs/example.py
tests/reraiseit_test.py
zerotk/__init__.py
zerotk.reraiseit.egg-info/PKG-INFO
zerotk.reraiseit.egg-info/SOURCES.txt
zerotk.reraiseit.egg-info/dependency_links.txt
zerotk.reraiseit.egg-info/namespace_packages.txt
zerotk.reraiseit.egg-info/requires.txt
zerotk.reraiseit.egg-info/top_level.txt
zerotk/reraiseit/__init__.py
zerotk/reraiseit/_reraiseit.py