Metadata-Version: 1.1
Name: zerotk.reraiseit
Version: 2.0.7
Summary: Reraise exceptions.
Home-page: https://github.com/zerotk/reraiseit
Author: Alexandre Andrade
Author-email: kaniabi@gmail.com
License: UNKNOWN
Keywords: exception,raise,reraise
Platform: UNKNOWN
Classifier: Development Status :: 5 - Production/Stable
Classifier: Intended Audience :: Developers
Classifier: Topic :: Software Development :: Libraries :: Python Modules
Classifier: License :: OSI Approved :: GNU General Public License v3 (GPLv3)
Classifier: Programming Language :: Python :: 2
Classifier: Programming Language :: Python :: 2.7
Classifier: Programming Language :: Python :: 3
Classifier: Programming Language :: Python :: 3.5
